cdxcore/__init__.py
cdxcore/config.py
cdxcore/deferred.py
cdxcore/dynalimits.py
cdxcore/dynaplot.py
cdxcore/err.py
cdxcore/jcpool.py
cdxcore/npio.py
cdxcore/npshm.py
cdxcore/pretty.py
cdxcore/subdir.py
cdxcore/uniquehash.py
cdxcore/util.py
cdxcore/verbose.py
cdxcore/version.py
cdxcore-0.1.57.dist-info/licenses/LICENSE
docs/source/conf.py
tests/__init__.py
tests/test_config.py
tests/test_deferred.py
tests/test_dynaplot.py
tests/test_err.py
tests/test_jcpool.py
tests/test_npio.py
tests/test_npshm.py
tests/test_pretty.py
tests/test_subdir.py
tests/test_uniquehash.py
tests/test_util.py
tests/test_verbose.py
tests/test_version.py
tmp/filelock.py
tmp/np.py
tmp/npsh1.py
tmp/sharedarray.py
up/git_message.py
up/pip_modify_setup.py
cdxcore-0.1.57.dist-info/METADATA
cdxcore-0.1.57.dist-info/WHEEL
cdxcore-0.1.57.dist-info/top_level.txt
cdxcore-0.1.57.dist-info/RECORD
